py_sio_ng_app/__about__.py
py_sio_ng_app/__init__.py
py_sio_ng_app/backend/__init__.py
py_sio_ng_app/backend/socketio_backend.py
py_sio_ng_app/backend/socketio_server.py
py_sio_ng_app/config/__init__.py
py_sio_ng_app/config/app.py
py_sio_ng_app/config/datadirs.py
py_sio_ng_app/config/logging.py
py_sio_ng_app/frontend/__init__.py
py_sio_ng_app/frontend/webview_angular.py
py_sio_ng_app-0.10.0.dist-info/METADATA
py_sio_ng_app-0.10.0.dist-info/WHEEL
py_sio_ng_app-0.10.0.dist-info/licenses/LICENSE.txt
py_sio_ng_app-0.10.0.dist-info/RECORD
