Metadata-Version: 2.3
Name: py-sio-ng-app
Version: 0.10.0
Summary: Base package for Python + SocketIO + Angular applications
Project-URL: Documentation, https://github.com/kliskatek/py-sio-ng-app#readme
Project-URL: Issues, https://github.com/kliskatek/py-sio-ng-app/issues
Project-URL: Source, https://github.com/kliskatek/py-sio-ng-app
Author-email: Ibon Zalbide <ibon.zalbie@kliskatek.com>
License: MIT
Classifier: Development Status :: 4 - Beta
Classifier: Programming Language :: Python
Classifier: Programming Language :: Python :: 3.8
Classifier: Programming Language :: Python :: 3.9
Classifier: Programming Language :: Python :: 3.10
Classifier: Programming Language :: Python :: 3.11
Classifier: Programming Language :: Python :: 3.12
Classifier: Programming Language :: Python :: Implementation :: CPython
Classifier: Programming Language :: Python :: Implementation :: PyPy
Requires-Python: >=3.8
Requires-Dist: dataclasses-json
Requires-Dist: eventlet
Requires-Dist: python-socketio
Requires-Dist: pywebview
